{"submission_id": "1075", "source": "#include <iostream>\r\n#include <string>\r\n#include <vector>\r\n#include <algorithm>\r\nusing namespace std;\r\nint main() {\r\n\tlong long n, m;\r\n\tlong long q[100000];\r\n\tcin >> n >> m;\r\n\tfor (long long i = 0; i < m; i++) {\r\n\t\tlong long a, b;\r\n\t\tcin >> a >> b;\r\n\t\tint o;\r\n\t\t//\u30bb\u30c3\u30c8\u6570\u306e\u5224\u5b9a\r\n\t\tif (n % a == 0) {\r\n\t\t\to = n / a;\r\n\t\t}\r\n\r\n\t\telse {\r\n\t\t\to= n / a + 1;\r\n\t\t}\r\n\t\tlong long y = a * b*o;\r\n\t\tq[i] = y;\r\n\t}\r\n\r\n\tlong long e = q[0];\r\n\tfor (long long i = 0; i < m; i++) {\r\n\t\tlong long u = q[i];\r\n\t\tif (e > u) {\r\n\t\t\te = u;\r\n\t\t}\r\n\t\r\n\t}\r\n\tcout << e << endl;\r\n}\r\n", "problem_id": "35", "problem_title": "\u725b\u4e3c\u306e\u6ce8\u6587", "datetime": "2018-08-06 16:08:43", "lang": "C++", "user": "shoji", "sample_io": ["Accepted"], "testcase": [{"result": "WrongAnswer", "max_score": "100", "io_result": ["WrongAnswer", "WrongAnswer", "WrongAnswer", "WrongAnswer", "WrongAnswer", "WrongAnswer"]}], "result": "WrongAnswer", "score": "0", "max_score": "100"}