{"submission_id": "1929", "source": "#include <utility>\r\n#include <iostream>\r\n#include <vector>\r\n#include <algorithm>\r\n#include <string>\r\n#include <map>\r\n#include <cmath>\r\n#include <numeric>\r\n#include <limits>\r\n#include <queue>\r\n#define ll long long int\r\n#define rep(i,rept) for (ll i = 0; i < rept; i++)\r\n#define Yes(b) std::cout<< (b ? \"Yes\" : \"No\")<<std::endl\r\n#define YES(b) std::cout<< (b ? \"YES\" : \"NO\")<<std::endl\r\n#define fr first\r\n#define se second\r\n#define se second\r\n#define lolo 92233720368547757\r\n#define susu 1000000007\r\n#define MAX_E 1002\r\n#define MAX_N 25100\r\n#define MAX_M 20100\r\nusing namespace std;\r\ntypedef pair<int, int> P;\r\nstruct edge {\r\n\tint to;\r\n\tchar cam;\r\n\tint cost;\r\n};\r\nint v;\r\nvector<edge> G[MAX_N];\r\nint d[MAX_N];\r\nint n, m;\r\n\r\nll dijkstra(int s,bool ac,bool bc,bool cc,bool dc) {\r\n\tpriority_queue<P, vector<P>, greater<P>>que;\r\n\tfill(d, d + n + 1, 2147483646);\r\n\td[s] = 0;\r\n\tque.push(P(0, s));\r\n\twhile (!que.empty()) {\r\n\t\tP p = que.top(); que.pop();\r\n\t\tint v = p.second;\r\n\t\tif (d[v] < p.first)continue;\r\n\t\tfor (int i = 0; i < G[v].size(); i++) {\r\n\t\t\tedge e = G[v][i];\r\n\t\t\tif (e.cam == 'A' && !ac) {\r\n\t\t\t\tcontinue;\r\n\t\t\t}\r\n\t\t\tif (e.cam == 'B' && !bc) {\r\n\t\t\t\tcontinue;\r\n\t\t\t}\r\n\t\t\tif (e.cam == 'C' && !cc) {\r\n\t\t\t\tcontinue;\r\n\t\t\t}\r\n\t\t\tif (e.cam == 'D'&&!dc) {\r\n\t\t\t\tcontinue;\r\n\t\t\t}\r\n\t\t\tif (d[e.to] > d[v] + e.cost) {\r\n\t\t\t\td[e.to] = d[v] + e.cost;\r\n\t\t\t\tque.push(P(d[e.to], e.to));\r\n\t\t\t}\r\n\t\t}\r\n\t}\r\n\treturn d[n];\r\n}\r\nint main() {\r\n\tedge edg;\r\n\tll jk = lolo;\r\n\tint h, k, l;\r\n\tint am, bm, cm, dm;\r\n\tchar s;\r\n\tcin >> n >> m;\r\n\tcin >> am >> bm >> cm >> dm;\r\n\trep(i, m) {\r\n\t\tcin >> h >> k >> s >> l;\r\n\t\tedg = { k,s,l };\r\n\t\tG[h].emplace_back(edg);\r\n\t\tedg = { h,s,l };\r\n\t\tG[k].emplace_back(edg);\r\n\t}\r\n\trep(i, 2) {\r\n\t\trep(j, 2) {\r\n\t\t\trep(q, 2) {\r\n\t\t\t\trep(o, 2) {\r\n\t\t\t\t\tjk = std::min(jk, (dijkstra(1, i, j, q, o) + (am*i + bm * j + cm * q + dm * o)));\r\n\t\t\t\t\t\r\n\t\t\t\t}\r\n\t\t\t}\r\n\t\t}\r\n\t}\r\n\tcout << jk << endl;\r\n\treturn 0;\r\n}", "problem_id": "52", "problem_title": "TRAVELER", "datetime": "2018-08-08 11:59:05", "lang": "C++", "user": "leaf2326", "sample_io": ["Accepted"], "testcase": [{"result": "Accepted", "max_score": "100", "io_result": ["Accepted", "Accepted", "Accepted", "Accepted", "Accepted"]}], "result": "Accepted", "score": "100", "max_score": "100"}