{"submission_id": "2007", "source": "#include <iostream>\r\n#include <algorithm>\r\n\r\nint main() {\r\n\r\n\tint N, M;\r\n\t\r\n\tstd::cin >> N >> M;\r\n\r\n\tint min = 100000000;  // \u6700\u4f4e\u9650\u652f\u6255\u3046\u5fc5\u8981\u306e\u3042\u308b\u304a\u91d1\r\n\tfor (int i = 0; i < M; ++i) {\r\n\t\t\r\n\t\tint a, b;\r\n\r\n\t\tstd::cin >> a >> b;\r\n\r\n\t\tif (N % a == 0) {\r\n\t\t\tmin = std::min(min, b * (N / a));\r\n\t\t}\r\n\t\telse {\r\n\t\t\tmin = std::min(min, b * (N / a ))\r\n\t\t}\r\n\t}\r\n\r\n\tstd::cout << min << std::endl;\r\n\r\n\treturn 0;\r\n}", "problem_id": "35", "problem_title": "\u725b\u4e3c\u306e\u6ce8\u6587", "datetime": "2018-08-14 16:19:07", "lang": "C++", "user": "papipupepo", "result": "CompileError", "score": "0", "max_score": "0"}